Workbook

Sheet README
B1: HDFC BANK - PERFORMANCE BENCHMARKING ANALYSIS
B2: Analyst: Akanksha Giri | Date: June 2026 | Data: FY2025 Annual Reports
B4: PURPOSE | C4: Benchmark HDFC Bank's key performance metrics against Indian banking peers (ICICI, Axis, Kotak) using the most recent full-year data (FY2025, year ending March 31 2025). Identify efficiency gaps and strategic opportunities.
B7: DATA SOURCES | C7: HDFC Bank Annual Report FY2025, ICICI Bank Annual Report FY2025, Axis Bank Annual Report FY2025, Kotak Mahindra Bank Annual Report FY2025. All figures publicly available from company investor relations pages.
B10: SHEETS | C10: 1. README 2. Raw Data -sourced inputs (blue text) 3. KPI Dashboard - calculated ratios 4. Peer Comparison -ranked benchmark table 5. Analyst Insights
B13: COLOR CODE | C13: Blue text = hardcoded inputs from annual reports | Black text = formulas | Green background = best-in-class | Orange background = lagging peer
B15: HOW TO USE | C15: Update blue cells in 'Raw Data' with new figures. All KPIs recalculate automatically.

Sheet Raw Data
B1: RAW DATA - FY2025 ANNUAL REPORT INPUTS (Year ending March 31, 2025)
B2: Source: Company Annual Reports FY2025 | All figures in ₹ Crore unless noted | Blue = hardcoded inputs
B4: METRIC | C4: HDFC Bank | D4: ICICI Bank | E4: Axis Bank | F4: Kotak Mah.
B5: INCOME STATEMENT
B6: Net Interest Income (NII) | C6: 122670.1 | D6: 81165 | E6: 54348 | F6: 28342
B7: other Income | C7: 45632.28 | D7: 28506.7 | E7: 25257 | F7: 14961.13
B8: Total Operating Income | C8: =SUM(C6:C7) -> 168302.38 | D8: =SUM(D6:D7) -> 109671.7 | E8: =SUM(E6:E7) -> 79605 | F8: =SUM(F6:F7) -> 43303.13
B9: Operating Expenses | C9: 68174.88 | D9: 42372 | E9: 37500 | F9: 18776.44
B10: Pre-Provision Profit (PPP) | C10: =C8-C9 -> 100127.5 | D10: =D8-D9 -> 67299.7 | E10: =E8-E9 -> 42105 | F10: =F8-F9 -> 24526.69
B11: Provisions & Contingencies | C11: 32780.131 | D11: 4683 | E11: 7759 | F11: 2942.36
B12: Net Profit (PAT) | C12: 67347.358 | D12: 47227 | E12: 26373 | F12: 16450.08
B14: BALANCE SHEET
B15: Total Assets | C15: 3910199 | D15: 2118240 | E15: 1609930 | F15: 879774
B16: Net Advances (Loans) | C16: 2619609 | D16: 1341766 | E16: 1040811 | F16: 426909.2
B17: Total Deposits | C17: 2714714.9 | D17: 1610348 | E17: 1172952 | F17: 494707
B18: CASA Deposits | C18: 944600 | D18: 673729 | E18: 478188 | F18: 214415.89
B19: Shareholders Equity | C19: 501424.6 | D19: 292076 | E19: 178617 | F19: 157395
B20: Gross NPA Ratio | C20: 0.0133 | D20: 0.0173 | E20: 0.0128 | F20: 0.014
B21: Net NPA Ratio | C21: 0.0043 | D21: 0.0039 | E21: 0.0033 | F21: 0.004
B23: OTHER INPUTS
B24: Number of Branches | C24: 9455 | D24: 6983 | E24: 5879 | F24: 2148
B25: Risk-Weighted Assets (RWA) | C25: 2660003.9 | D25: 1611104.4 | E25: 1154074.6 | F25: 519614.54
B26: Tier 1 Capital Ratio | C26: 0.1769 | D26: 0.1594 | E26: 0.1507 | F26: 0.211
B28: Note: Figures sourced from FY2025 Annual Reports (year ending March 31, 2025). Minor rounding applied.

Sheet Peer Comparison
B1: PEER COMPARISON — RANKED BENCHMARKING TABLE (FY2025)
B2: Green = Sector leader | Orange = Lagging | All ratios calculated from Raw Data sheet
B4: KPI | C4: HDFC | D4: ICICI | E4: Axis | F4: Kotak | G4: Leader | H4: Strategic Implication
B5: NIM (%) | C5: =3.48% -> 0.0348 | D5: =4.32% -> 0.0432 | E5: =3.98% -> 0.0398 | F5: =4.96% -> 0.0496 | G5: ='KPI Dashboard'!F4 -> Kotak Mah. | H5: Kotak earns highest spread per ₹ of assets - superior loan pricing power
B6: RoA (%) | C6: ='Raw Data'!C12/'Raw Data'!C15 -> 0.017223512 | D6: ='Raw Data'!D12/'Raw Data'!D15 -> 0.022295396 | E6: ='Raw Data'!E12/'Raw Data'!E15 -> 0.016381458 | F6: ='Raw Data'!F12/'Raw Data'!F15 -> 0.018698075 | G6: ='KPI Dashboard'!D4 -> ICICI Bank | H6: ICICI leads on asset productivity - strongest earnings engine at scale
B7: RoE (%) | C7: ='Raw Data'!C12/'Raw Data'!C19 -> 0.13431203 | D7: ='Raw Data'!D12/'Raw Data'!D19 -> 0.16169422 | E7: ='Raw Data'!E12/'Raw Data'!E19 -> 0.14765112 | F7: ='Raw Data'!F12/'Raw Data'!F19 -> 0.10451463 | G7: ='KPI Dashboard'!D4 -> ICICI Bank | H7: ICICI delivers highest shareholder return - capital efficiency advantage
B8: Cost-to-Income (%) | C8: ='Raw Data'!C9/'Raw Data'!C8 -> 0.40507377 | D8: ='Raw Data'!D9/'Raw Data'!D8 -> 0.38635309 | E8: ='Raw Data'!E9/'Raw Data'!E8 -> 0.47107594 | F8: ='Raw Data'!F9/'Raw Data'!F8 -> 0.43360468 | G8: ='KPI Dashboard'!D4 -> ICICI Bank | H8: ICICI most operationally lean - HDFC has meaningful room to reduce CIR
B9: Gross NPA (%) | C9: ='Raw Data'!C20 -> 0.0133 | D9: ='Raw Data'!D20 -> 0.0173 | E9: ='Raw Data'!E20 -> 0.0128 | F9: ='Raw Data'!F20 -> 0.014 | G9: ='KPI Dashboard'!E4 -> Axis Bank | H9: Axis has cleanest book
B10: CASA Ratio (%) | C10: ='Raw Data'!C18/'Raw Data'!C17 -> 0.34795551 | D10: ='Raw Data'!D18/'Raw Data'!D17 -> 0.41837479 | E10: ='Raw Data'!E18/'Raw Data'!E17 -> 0.40767909 | F10: ='Raw Data'!F18/'Raw Data'!F17 -> 0.43341996 | G10: ='KPI Dashboard'!F4 -> Kotak Mah. | H10: Kotak has cheapest funding mix - structural cost-of-funds advantage
B11: Tier 1 Ratio (%) | C11: ='Raw Data'!C26 -> 0.1769 | D11: ='Raw Data'!D26 -> 0.1594 | E11: ='Raw Data'!E26 -> 0.1507 | F11: ='Raw Data'!F26 -> 0.211 | G11: ='KPI Dashboard'!F4 -> Kotak Mah. | H11: Kotak most well-capitalised - lowest regulatory and solvency risk

Sheet KPI Dashboard
B1: KPI DASHBOARD - CALCULATED RATIOS FY2025
B2: Data flows from Peer Comparisons | Green = Best-in-class | Orange = Lagging
B4: KPI | C4: HDFC Bank | D4: ICICI Bank | E4: Axis Bank | F4: Kotak Mah. | G4: What It Measures
B5: PROFITABILITY
B6: Net Interest Margin (NIM) | C6: ='Peer Comparison'!C5 -> 0.0348 | D6: ='Peer Comparison'!D5 -> 0.0432 | E6: ='Peer Comparison'!E5 -> 0.0398 | F6: ='Peer Comparison'!F5 -> 0.0496 | G6: Higher = stronger lending profitability
B7: Return on Assets (RoA) | C7: ='Peer Comparison'!C6 -> 0.017223512 | D7: ='Peer Comparison'!D6 -> 0.022295396 | E7: ='Peer Comparison'!E6 -> 0.016381458 | F7: ='Peer Comparison'!F6 -> 0.018698075 | G7: Higher = more efficient utilisation of total assets.
B8: Return on Equity (RoE) | C8: ='Peer Comparison'!C7 -> 0.13431203 | D8: ='Peer Comparison'!D7 -> 0.16169422 | E8: ='Peer Comparison'!E7 -> 0.14765112 | F8: ='Peer Comparison'!F7 -> 0.10451463 | G8: Higher = Returns generated for shareholders
B9: EFFICIENCY
B10: Cost-to-Income Ratio (CIR) | C10: ='Raw Data'!C9/'Raw Data'!C8 -> 0.40507377 | D10: ='Raw Data'!D9/'Raw Data'!D8 -> 0.38635309 | E10: ='Raw Data'!E9/'Raw Data'!E8 -> 0.47107594 | F10: ='Raw Data'!F9/'Raw Data'!F8 -> 0.43360468 | G10: Lower = more efficient cost management.
B11: Cost per Branch (₹ Cr) | C11: ='Raw Data'!C9/'Raw Data'!C24 -> 7.210458 | D11: ='Raw Data'!D9/'Raw Data'!D24 -> 6.0678791 | E11: ='Raw Data'!E9/'Raw Data'!E24 -> 6.3786358 | F11: ='Raw Data'!F9/'Raw Data'!F24 -> 8.7413594 | G11: Lower = more cost-efficient branch operations.
B12: ASSET QUALITY
B13: Gross NPA Ratio | C13: ='Peer Comparison'!C9 -> 0.0133 | D13: ='Peer Comparison'!D9 -> 0.0173 | E13: ='Peer Comparison'!E9 -> 0.0128 | F13: ='Peer Comparison'!F9 -> 0.014 | G13: Lower = better asset quality
B14: Net NPA Ratio | C14: ='Raw Data'!C21 -> 0.0043 | D14: ='Raw Data'!D21 -> 0.0039 | E14: ='Raw Data'!E21 -> 0.0033 | F14: ='Raw Data'!F21 -> 0.004 | G14: Lower = stronger loan recovery and provisioning quality.
B15: LIQUIDITY & FUNDING
B16: CASA Ratio | C16: ='Peer Comparison'!C10 -> 0.34795551 | D16: ='Peer Comparison'!D10 -> 0.41837479 | E16: ='Peer Comparison'!E10 -> 0.40767909 | F16: ='Peer Comparison'!F10 -> 0.43341996 | G16: Higher = cheaper funding
B17: Credit-Deposit (CD) Ratio | C17: ='Raw Data'!C16/'Raw Data'!C17 -> 0.96496652 | D17: ='Raw Data'!D16/'Raw Data'!D17 -> 0.83321493 | E17: ='Raw Data'!E16/'Raw Data'!E17 -> 0.88734322 | F17: ='Raw Data'!F16/'Raw Data'!F17 -> 0.86295363 | G17: Optimal range = balanced lending and liquidity management.
B18: CAPITAL ADEQUACY
B19: Tier 1 Capital Ratio | C19: ='Peer Comparison'!C11 -> 0.1769 | D19: ='Peer Comparison'!D11 -> 0.1594 | E19: ='Peer Comparison'!E11 -> 0.1507 | F19: ='Peer Comparison'!F11 -> 0.211 | G19: Higher = stronger capital adequacy and financial resilience.

Sheet Analyst Insights
B1: ANALYST INSIGHTS - HDFC BANK PEER BENCHMARKING COMMENTARY
B2: Author: Akanksha Giri | Data: FY2025 Annual Reports | Coverage: HDFC, ICICI, Axis, Kotak
B4: EXECUTIVE SUMMARY
B5: This analysis benchmarks HDFC Bank against three private sector peers - ICICI, Axis, and Kotak across five performance areas using FY2025 data. The overall picture shows HDFC is a solid, well-run bank but not the outright leader in any single category. Kotak leads on profitability and capital strength. ICICI leads on efficiency. HDFC's clearest advantage is its funding base. Axis consistently trails the group.
B7: 1. PROFITABILITY - KOTAK LEADS, HDFC IS MID-TABLE
B8: Kotak Mahindra is the standout performer - highest NIM (4.96%), highest RoA (1.87% vs HDFC's 1.72%), and the only bank with RoE above 10% adjusted for scale pressures. ICICI leads on RoE at 16.17%, while HDFC at 13.43% is the second-lowest in the group. HDFC's large balance sheet works against it here - more assets to generate returns from means the ratios are harder to move.
B10: 2. EFFICIENCY - ICICI IS THE BENCHMARK TO BEAT
B11: ICICI's CIR of 38.64% is the best in the group by a clear margin. HDFC at 40.51% is second, which is actually a creditable position - Axis at 47.11% and Kotak at 43.36% both lag. On cost per branch, ICICI again leads at ₹6.07 Cr vs HDFC's ₹7.21 Cr. The message is that HDFC is reasonably efficient, but ICICI runs a tighter operation.
B13: 3. ASSET QUALITY - HDFC AND AXIS TIE FOR BEST BOOK
B14: This is HDFC's strongest area. Gross NPA of 1.33% is the lowest in the peer group alongside Axis (1.28%). Net NPA of 0.43% is also sector-leading. ICICI carries the highest NPA burden at 1.73% Gross and 0.39% Net. Clean asset quality means HDFC spends less on provisions - protecting profitability even when the economy slows.
B16: 4. FUNDING STRENGTH - KOTAK HAS THE CHEAPEST DEPOSITS
B17: Kotak leads CASA at 43.34%, with ICICI close behind at 41.84%. HDFC at 34.80% is actually the lowest in the group - a notable shift from its historical strength. This matters because a lower CASA ratio means HDFC pays more to fund its loans, which directly pressures margins. On CD ratio, HDFC at 96.50% is the most stretched lender - lending out nearly all its deposits, leaving limited buffer.
... B23: All figures sourced from FY2025 Annual Reports published by each company on their investor relations pages (year ending March 31, 2025). Ratios are independently calculated; minor variance from company-disclosed figures may reflect rounding or definitional differences. This is an independent analytical exercise and does not constitute investment advice.
